LICENSE.txt
MANIFEST.in
README.md
gssapi-console.py
setup.py
gssapi_console/__init__.py
gssapi_console/core.py
gssapi_console/drivers.py
gssapi_console/yalpt_driver.py
gssapi_console.egg-info/PKG-INFO
gssapi_console.egg-info/SOURCES.txt
gssapi_console.egg-info/dependency_links.txt
gssapi_console.egg-info/entry_points.txt
gssapi_console.egg-info/requires.txt
gssapi_console.egg-info/top_level.txt