Metadata-Version: 1.1
Name: gssapi-console
Version: 1.0.0
Summary: An interactive tool for testing Python GSSAPI programs
Home-page: https://github.com/pythongssapi/python-gssapi
Author: The Python GSSAPI Team
Author-email: sross@redhat.com
License: LICENSE.txt
Keywords: gssapi,security
Platform: UNKNOWN
Classifier: Development Status :: 4 - Beta
Classifier: Programming Language :: Python
Classifier: Programming Language :: Python :: 2.7
Classifier: Programming Language :: Python :: 3
Classifier: Programming Language :: Python :: 3.3
Classifier: Programming Language :: Python :: 3.4
Classifier: Programming Language :: Python :: 3.5
Classifier: Intended Audience :: Developers
Classifier: License :: OSI Approved :: ISC License (ISCL)
Classifier: Programming Language :: Python :: Implementation :: CPython
Classifier: Topic :: Security
